Metadata-Version: 2.1
Name: odoo14-addon-website-sale-suggest-create-account
Version: 14.0.1.0.2.dev4
Summary: Suggest users to create an account when buying in the website
Home-page: https://github.com/OCA/e-commerce
Author: Tecnativa, LasLabs, Odoo Community Association (OCA)
Author-email: support@odoo-community.org
License: LGPL-3
Platform: UNKNOWN
Classifier: Programming Language :: Python
Classifier: Framework :: Odoo
Classifier: Framework :: Odoo :: 14.0
Classifier: License :: OSI Approved :: GNU Lesser General Public License v3 (LGPLv3)
Requires-Python: >=3.6
Requires-Dist: odoo <14.1dev,>=14.0a
